koji_cli_plugins/kojismokydingometa.py
kojismokydingo/__init__.py
kojismokydingo/archives.py
kojismokydingo/builds.py
kojismokydingo/clients.py
kojismokydingo/common.py
kojismokydingo/dnf.py
kojismokydingo/hosts.py
kojismokydingo/py.typed
kojismokydingo/rpm.py
kojismokydingo/tags.py
kojismokydingo/types.py
kojismokydingo/users.py
kojismokydingo/cli/__init__.py
kojismokydingo/cli/archives.py
kojismokydingo/cli/builds.py
kojismokydingo/cli/clients.py
kojismokydingo/cli/hosts.py
kojismokydingo/cli/sift.py
kojismokydingo/cli/tags.py
kojismokydingo/cli/users.py
kojismokydingo/sift/__init__.py
kojismokydingo/sift/builds.py
kojismokydingo/sift/common.py
kojismokydingo/sift/parse.py
kojismokydingo/sift/tags.py
kojismokydingo/standalone/__init__.py
kojismokydingo/standalone/builds.py
kojismokydingo/standalone/tags.py
kojismokydingo-2.2.0.dist-info/LICENSE
kojismokydingo-2.2.0.dist-info/METADATA
kojismokydingo-2.2.0.dist-info/WHEEL
kojismokydingo-2.2.0.dist-info/entry_points.txt
kojismokydingo-2.2.0.dist-info/top_level.txt
kojismokydingo-2.2.0.dist-info/RECORD
