Metadata-Version: 2.1
Name: kojismokydingo
Version: 2.2.0
Summary: A collection of Koji client plugins and utils
Home-page: https://github.com/obriencj/koji-smoky-dingo
Author: Christopher O'Brien
Author-email: obriencj@gmail.com
License: GNU General Public License v3 (GPLv3)
Project-URL: Source, https://github.com/obriencj/koji-smoky-dingo
Project-URL: Bug Reports, https://github.com/obriencj/koji-smoky-dingo/issues
Project-URL: Documentation, https://obriencj.github.io/koji-smoky-dingo
Project-URL: Discussions, https://obriencj.github.io/koji-smoky-dingo/discussions
Platform: any
Classifier: Development Status :: 5 - Production/Stable
Classifier: Environment :: Console
Classifier: Intended Audience :: Developers
Classifier: License :: OSI Approved :: GNU General Public License v3 (GPLv3)
Classifier: Natural Language :: English
Classifier: Programming Language :: Python :: 3
Classifier: Programming Language :: Python :: 3.6
Classifier: Programming Language :: Python :: 3.7
Classifier: Programming Language :: Python :: 3.8
Classifier: Programming Language :: Python :: 3.9
Classifier: Programming Language :: Python :: 3.10
Classifier: Programming Language :: Python :: 3.11
Classifier: Programming Language :: Python :: 3.12
Classifier: Topic :: Software Development :: Build Tools
Classifier: Topic :: Utilities
License-File: LICENSE
Requires-Dist: appdirs
Requires-Dist: koji
Requires-Dist: typing-extensions ; python_version < "3.10"
